FloriaConsoleGUI/Config.py
FloriaConsoleGUI/Converter.py
FloriaConsoleGUI/Core.py
FloriaConsoleGUI/Func.py
FloriaConsoleGUI/Log.py
FloriaConsoleGUI/__init__.py
FloriaConsoleGUI/Classes/Anchor.py
FloriaConsoleGUI/Classes/AnsiColor.py
FloriaConsoleGUI/Classes/Buffer.py
FloriaConsoleGUI/Classes/Counter.py
FloriaConsoleGUI/Classes/Event.py
FloriaConsoleGUI/Classes/Keys.py
FloriaConsoleGUI/Classes/Orientation.py
FloriaConsoleGUI/Classes/Vec.py
FloriaConsoleGUI/Classes/__init__.py
FloriaConsoleGUI/Graphic/Animation.py
FloriaConsoleGUI/Graphic/BaseGraphicObject.py
FloriaConsoleGUI/Graphic/Drawer.py
FloriaConsoleGUI/Graphic/Pixel.py
FloriaConsoleGUI/Graphic/Shaders.py
FloriaConsoleGUI/Graphic/__init__.py
FloriaConsoleGUI/Graphic/Shaders/BasePixelShader.py
FloriaConsoleGUI/Graphic/Shaders/InvertPixelShader.py
FloriaConsoleGUI/Graphic/Shaders/NoisePixelShader.py
FloriaConsoleGUI/Graphic/Shaders/RainbowPixelShader.py
FloriaConsoleGUI/Graphic/Shaders/__init__.py
FloriaConsoleGUI/Graphic/Widgets/Button.py
FloriaConsoleGUI/Graphic/Widgets/Container.py
FloriaConsoleGUI/Graphic/Widgets/InteractiveWidget.py
FloriaConsoleGUI/Graphic/Widgets/Label.py
FloriaConsoleGUI/Graphic/Widgets/Media.py
FloriaConsoleGUI/Graphic/Widgets/TextBox.py
FloriaConsoleGUI/Graphic/Widgets/Widget.py
FloriaConsoleGUI/Graphic/Widgets/__init__.py
FloriaConsoleGUI/Graphic/Windows/TitledWindow.py
FloriaConsoleGUI/Graphic/Windows/Window.py
FloriaConsoleGUI/Graphic/Windows/__init__.py
FloriaConsoleGUI/Managers/AnimationManager.py
FloriaConsoleGUI/Managers/KeyboardManager.py
FloriaConsoleGUI/Managers/Parser.py
FloriaConsoleGUI/Managers/SoundManager.py
FloriaConsoleGUI/Managers/WindowManager.py
FloriaConsoleGUI/Managers/__init__.py
FloriaConsoleGUI/Threads/BaseThread.py
FloriaConsoleGUI/Threads/GraphicThread.py
FloriaConsoleGUI/Threads/InputThread.py
FloriaConsoleGUI/Threads/SimulationThread.py
FloriaConsoleGUI/Threads/__init__.py
FloriaConsoleGUI-1.2.dist-info/LICENSE
FloriaConsoleGUI-1.2.dist-info/METADATA
FloriaConsoleGUI-1.2.dist-info/WHEEL
FloriaConsoleGUI-1.2.dist-info/top_level.txt
FloriaConsoleGUI-1.2.dist-info/zip-safe
FloriaConsoleGUI-1.2.dist-info/RECORD
